{"cookies":[{"name":"csrftoken","value":"AIQT5gtGoO18Gm1HasH5iV","domain":".instagram.com","path":"/","expires":1770007945.438318,"httpOnly":false,"secure":true,"sameSite":"Lax"},{"name":"datr","value":"gEugZ8YODAgHqzBd-MGrjlOp","domain":".instagram.com","path":"/","expires":1773118337.492781,"httpOnly":true,"secure":true,"sameSite":"None"},{"name":"ig_did","value":"A2A7167B-928C-4567-B9EB-0BB1570C4798","domain":".instagram.com","path":"/","expires":1770094343.940813,"httpOnly":true,"secure":true,"sameSite":"Lax"},{"name":"wd","value":"1366x768","domain":".instagram.com","path":"/","expires":1739163145,"httpOnly":false,"secure":true,"sameSite":"Lax"},{"name":"mid","value":"Z6BLgQALAAFu616JGu1-UZ-WZSTf","domain":".instagram.com","path":"/","expires":1773118338.367721,"httpOnly":false,"secure":true,"sameSite":"Lax"},{"name":"ig_nrcb","value":"1","domain":".instagram.com","path":"/","expires":1770094338.367768,"httpOnly":false,"secure":true,"sameSite":"Lax"},{"name":"sessionid","value":"69052761682%3AN1QBVgGogVSvbP%3A16%3AAYeEgqV82XC4xJQhb8x9o_tty4TsSBFy7SCxitL5-g","domain":".instagram.com","path":"/","expires":1770094343.940661,"httpOnly":true,"secure":true,"sameSite":"Lax"},{"name":"ds_user_id","value":"69052761682","domain":".instagram.com","path":"/","expires":1746334345.438401,"httpOnly":false,"secure":true,"sameSite":"Lax"},{"name":"ps_l","value":"1","domain":".instagram.com","path":"/","expires":1773118344.826167,"httpOnly":true,"secure":true,"sameSite":"Lax"},{"name":"ps_n","value":"1","domain":".instagram.com","path":"/","expires":1773118344.826228,"httpOnly":true,"secure":true,"sameSite":"None"},{"name":"dpr","value":"1","domain":".instagram.com","path":"/","expires":1739163145,"httpOnly":false,"secure":true,"sameSite":"None"},{"name":"rur","value":"\"HIL\\05469052761682\\0541770094344:01f7a99058a6fe25856da399d716d57c5f7e9206782108777e767a37dd0719dd9aa29961\"","domain":".instagram.com","path":"/","expires":-1,"httpOnly":true,"secure":true,"sameSite":"Lax"}],"origins":[{"origin":"https://www.instagram.com","localStorage":[{"name":"chatd-deviceid","value":"3202f9b8-1e8f-4f80-ab5f-bf03803788db"},{"name":"hb_timestamp","value":"1738558338271"},{"name":"IGSession","value":"8r967z:1738560145440"},{"name":"pigeon_state","value":"{\"lastDeviceInfoTime\":0}"},{"name":"mutex_polaris_banzai","value":"rjyne4:1738558346439"},{"name":"signal_flush_timestamp","value":"1738558338293"},{"name":"Session","value":"cvdj3z:1738558380440"},{"name":"mutex_banzai","value":"rjyne4:1738558346439"},{"name":"banzai:last_storage_flush","value":"1738558339051"}]}]}